opentdf.cpython-311-aarch64-linux-gnu.so
opentdf-1.5.5.dist-info/LICENSE
opentdf-1.5.5.dist-info/top_level.txt
opentdf-1.5.5.dist-info/WHEEL
opentdf-1.5.5.dist-info/RECORD
opentdf-1.5.5.dist-info/METADATA
